common_toolkit/__init__.py
common_toolkit/CLIs/__init__.py
common_toolkit/CLIs/development_cli/__init__.py
common_toolkit/CLIs/development_cli/create_python_app.py
common_toolkit/CLIs/penetration_cli/__init__.py
common_toolkit/development/__init__.py
common_toolkit/development/dev_test1/__init__.py
common_toolkit/development/dev_test1/test1.py
common_toolkit/development/dev_test1/test2.py
common_toolkit/development/dev_test2/__init__.py
common_toolkit/development/email/__init__.py
common_toolkit/development/email/send_email.py
common_toolkit/penetration/__init__.py
common_toolkit-0.0.1.dist-info/entry_points.txt
common_toolkit-0.0.1.dist-info/LICENSE
common_toolkit-0.0.1.dist-info/WHEEL
common_toolkit-0.0.1.dist-info/METADATA
common_toolkit-0.0.1.dist-info/RECORD
