Metadata-Version: 2.1
Name: common_toolkit
Version: 0.0.1
Summary: Common Toolkit
Author-email: Lonely_Mr_Zhang <1371028681@qq.com>
Requires-Python: >=3.8.5
Classifier: License :: OSI Approved :: MIT License
Requires-Dist: pre-commit == 2.16.0 ; extra == "dev"
Requires-Dist: flake8 == 3.9.2 ; extra == "dev"
Requires-Dist: pytest == 6.2.1 ; extra == "dev"
Project-URL: Home, https://github.com/Lonely-Mr-zhang/common_toolkit
Provides-Extra: dev
Provides-Extra: development
Provides-Extra: penetration
